deanerfi/__init__.py
deanerfi/bootstrap.py
deanerfi/main.py
deanerfi/scanner.py
deanerfi/arb/__init__.py
deanerfi/arb/_arbitrageur.py
deanerfi/arb/_router.py
deanerfi/arb/api.py
deanerfi/common/__init__.py
deanerfi/common/msgbus.py
deanerfi/common/log/__init__.py
deanerfi/common/log/_config.py
deanerfi/common/log/_dtypes.py
deanerfi/common/log/_logger.py
deanerfi/common/log/api.py
deanerfi/data/__init__.py
deanerfi/data/erc20-abi.json
deanerfi/data/uniswap-v2-abis.json
deanerfi/dex/__init__.py
deanerfi/dex/_adaptors.py
deanerfi/dex/_config.py
deanerfi/dex/_dtypes.py
deanerfi/dex/_repo.py
deanerfi/dex/_uniswap.py
deanerfi/dex/api.py
deanerfi/dex/exceptions.py
deanerfi/modules/__init__.py
deanerfi/modules/dex_trade_watch.py
deanerfi/utils/__init__.py
deanerfi/utils/data.py
deanerfi/utils/graphql.py
deanerfi/utils/mongodb.py
deanerfi/utils/rabbitmq.py
deanerfi/utils/redis.py
deanerfi/utils/w3.py
deanerfi/w3/__init__.py
deanerfi/w3/_adaptor.py
deanerfi/w3/_config.py
deanerfi/w3/_dtypes.py
deanerfi/w3/api.py
deanerfi/w3/exceptions.py
deanerfi/w3/_repos/__init__.py
deanerfi/w3/_repos/_chains.py
deanerfi/w3/_repos/_contracts.py
deanerfi/w3/_repos/_tokens.py
deanerfi-0.1.0.dist-info/METADATA
deanerfi-0.1.0.dist-info/WHEEL
deanerfi-0.1.0.dist-info/top_level.txt
deanerfi-0.1.0.dist-info/RECORD
