Metadata-Version: 2.1
Name: deanerfi
Version: 0.1.0
Summary: Python tools for defi
Home-page: https://github.com/0xdeaner/deanerfi-core
Author: deaner
Author-email: Oxdeaner@gmail.com
License: None
Keywords: deanerfi
Platform: UNKNOWN
Classifier: Development Status :: 2 - Pre-Alpha
Classifier: Intended Audience :: Developers
Classifier: License :: OSI Approved :: MIT License
Classifier: Natural Language :: English
Classifier: Programming Language :: Python :: 3
Classifier: Programming Language :: Python :: 3.6
Classifier: Programming Language :: Python :: 3.7
Classifier: Programming Language :: Python :: 3.8
Requires-Python: >=3.6
Requires-Dist: pymongo (>=4.1.1)
Requires-Dist: requests (>=2.27.1)
Requires-Dist: httpx (>=0.23.0)
Requires-Dist: web3 (>=5.29.2)
Requires-Dist: networkx (>=2.8.3)
